prepress/__init__.py
prepress/cli.py
prepress/core/drivers/base.py
prepress/core/drivers/changelog.py
prepress/core/drivers/node.py
prepress/core/drivers/python.py
prepress/core/drivers/rust.py
prepress/templates/CHANGELOG.md
prepress/templates/python_publish.yml
prepress-0.1.2.dist-info/METADATA
prepress-0.1.2.dist-info/WHEEL
prepress-0.1.2.dist-info/entry_points.txt
prepress-0.1.2.dist-info/licenses/LICENSE
prepress-0.1.2.dist-info/RECORD
