Metadata-Version: 2.4
Name: prepress
Version: 0.1.2
Summary: A modern, polyglot release management tool
Project-URL: Homepage, https://omneity-labs.github.io/prepress/
Project-URL: Repository, https://github.com/omneity-labs/prepress
Project-URL: Documentation, https://github.com/omneity-labs/prepress/blob/main/GUIDE.md
Author-email: Omar Kamali <prepress@omneitylabs.com>
License: MIT
License-File: LICENSE
Requires-Python: >=3.10
Requires-Dist: libcst>=1.1.0
Requires-Dist: rich>=13.0.0
Requires-Dist: semver>=3.0.0
Requires-Dist: tomli>=2.0.1; python_version < '3.11'
Requires-Dist: typer>=0.9.0
Provides-Extra: test
Requires-Dist: pytest>=7.0.0; extra == 'test'
